Ceasar_encryptage/__init__.py
Ceasar_encryptage/encrypt.py
Ceasar_encryptage/main.py
Ceasar_encryptage-1.0.1.dist-info/LICENSE.txt
Ceasar_encryptage-1.0.1.dist-info/METADATA
Ceasar_encryptage-1.0.1.dist-info/WHEEL
Ceasar_encryptage-1.0.1.dist-info/top_level.txt
Ceasar_encryptage-1.0.1.dist-info/RECORD
