Metadata-Version: 2.1
Name: Ceasar-encryptage
Version: 1.0.1
Summary: c'est un algoritme de cryptage classique
Author: Cyberwolf
Author-email: ralphsaintil0@gmail.com
Classifier: Programming Language :: Python :: 3
Classifier: License :: OSI Approved :: MIT License
Classifier: Operating System :: OS Independent
License-File: LICENSE.txt
Requires-Dist: cryptography
